{
  "title": "Manhwas (Completed)",
  "description": "---------------------------_________________---------------------------",
  "artist": "---",
  "author": "---",
  "cover": "",
  "chapters": {
    "1": {
      "title": "Soothe Me",
      "volume": "1",
      "last_updated": "1637891751",
      "groups": {
        "": "/proxy/api/imgur/chapter/e7kAiRZ"
      }
    },
    "2": {
      "title": "The woman who lives in my room",
      "volume": "1",
      "last_updated": "1637892359",
      "groups": {
        "": "/proxy/api/imgur/chapter/tZL3uCR"
      }
    }
  }
}